blackboxoptim-1.1.0.dist-info/METADATA
blackboxoptim-1.1.0.dist-info/WHEEL
blackboxoptim-1.1.0.dist-info/entry_points.txt
blackboxoptim-1.1.0.dist-info/licenses/LICENSE
blackboxoptim/acquisition.py
blackboxoptim/gp.py
blackboxoptim/optimize.py
blackboxoptim/problem.py
blackboxoptim/rbf.py
blackboxoptim/sampling.py
blackboxoptim-1.1.0.dist-info/RECORD
