Metadata-Version: 2.1
Name: blackboxoptim
Version: 1.1.0
Summary: Solve black-box optimization problems using surrogate-based algorithms
Keywords: optimization,surrogate,black-box,RBF,GP
Author-Email: Weslley da Silva Pereira <weslley.dasilvapereira@nrel.gov>
License: Copyright (c) 2025 Alliance for Sustainable Energy, LLC
Classifier: License :: OSI Approved :: GNU General Public License (GPL)
Classifier: Programming Language :: Python
Classifier: Programming Language :: Python :: 3
Project-URL: Homepage, https://github.com/NREL/blackboxoptim
Project-URL: Docs, https://nrel.github.io/blackboxoptim
Requires-Python: >=3.9
Requires-Dist: numpy
Requires-Dist: scipy
Requires-Dist: pymoo
Requires-Dist: scikit-learn
